DESCRIPTION.rst
LICENSE.txt
MANIFEST.in
README.md
setup.cfg
setup.py
stslib/__init__.py
stslib/_version.py
stslib/async.py
stslib/colors.py
stslib/core.py
stslib/local_config.py
stslib/logd.py
stslib/refactor.py
stslib/seed.py
stslib/statics.py
stslib/vault.py