Metadata-Version: 1.2
Name: stslib
Version: 0.3.12
Summary: Library for bulk generation of Amazon STS temporary credentials
Home-page: https://github.com/fstab50/stslib
Author: Blake Huber
Author-email: blakeca00@gmail.com
License: GPL-3.0
Keywords: Amazon Web Services iam credentials AWS access key secret key
Platform: UNKNOWN
Classifier: Development Status :: 3 - Alpha
Classifier: Programming Language :: Python :: 3.5
Classifier: Programming Language :: Python :: 3.6
Classifier: License :: OSI Approved :: GNU General Public License v3 (GPLv3)
Classifier: Operating System :: POSIX :: Linux
Requires-Python: >=3.5, <4
